README.md
pyproject.toml
setup.py
app/__init__.py
app/main.py
app/models.py
calculadora_lib/__init__.py
calculadora_lib/operations.py
calculator_lib_terts.egg-info/PKG-INFO
calculator_lib_terts.egg-info/SOURCES.txt
calculator_lib_terts.egg-info/dependency_links.txt
calculator_lib_terts.egg-info/top_level.txt
test_lib/__init__.py
test_lib/test_lib_main.py
tests/__init__.py
tests/test_main.py